<?xml version="1.0" encoding="utf-8" standalone="yes"?>
	<addons><addon id="plugin.git.browser" version="2.0.0" name="Git Browser" author="azzy9"><requires><import addon="xbmc.python" version="3.0.0" /><import addon="script.module.requests" /><import addon="script.module.beautifulsoup4" /><import addon="script.module.myconnpy" option="true" /></requires><extension point="xbmc.python.pluginsource" library="addon.py"><provides>executable</provides></extension><extension point="xbmc.service" library="service.py" start="startup"/><extension point="xbmc.addon.metadata"><summary lang="en">Install Kodi Addons directly from GitHub</summary><description lang="en">Git Browser for Kodi. Using this tool, you'll be able to install any Kodi addon that is developed or distributed through GitHub.</description><disclaimer lang="en">Kodi is a registered trademark of the XBMC Foundation. We are not connected to or in any other way affiliated with Kodi, Team Kodi, or the XBMC Foundation. Furthermore, any software, addons, or products offered by us will receive no support in official Kodi channels, including the Kodi forums and various social networks.</disclaimer><language>en</language><platform>all</platform><assets><icon>icon.png</icon><fanart>fanart.jpg</fanart></assets></extension></addon>
<?xml version="1.0" encoding="UTF-8" standalone="yes" ?><addon id="plugin.video.kick" name="Kick" version="1.0.0" provider-name="azzy9"><requires><import addon="script.module.requests"/><import addon="script.module.six"/><import addon="inputstream.adaptive"/></requires><extension point="xbmc.python.pluginsource" library="main.py"><provides>video</provides></extension><extension point="xbmc.addon.metadata"><description lang="en">Kick</description><summary lang="en">Kick</summary><language>en</language><platform>all</platform><assets><icon>resources/icon.png</icon><fanart>resources/fanart.jpg</fanart></assets></extension></addon>
<addon id="plugin.video.lbryplus" name="LBRY+" version="0.8.0" provider-name="azzy9"><requires><import addon="script.module.routing" version="0.2.3"/><import addon="script.module.requests" version="2.22.0"/><import addon="script.module.six"/></requires><extension point="xbmc.python.pluginsource" library="lbry.py"><provides>video</provides></extension><extension point="xbmc.addon.metadata"><summary lang="en_GB">Plugin for LBRY and Odysee</summary><description lang="en_GB">LBRY is a secure, open, and community-run digital marketplace</description><platform>all</platform><license>GPL-2.0-or-later</license><source>https://github.com/azzy9/plugin.video.lbryplus</source><assets><icon>resources/assets/256x256.png</icon><fanart>resources/assets/fanart.jpg</fanart></assets></extension></addon>
<addon id="plugin.video.rumble" name="Rumble" version="1.9.2" provider-name="azzy9"><requires><import addon="script.module.simplejson"/><import addon="script.module.requests"/><import addon="script.module.six"/><import addon="inputstream.adaptive"/></requires><extension point="xbmc.python.pluginsource" library="main.py"><provides>video</provides></extension><extension point="xbmc.addon.metadata"><summary lang="en">Watch rumble videos.</summary><summary lang="pt_br">Assista videos do rumble.</summary><description lang="en">Watch uncensored videos with rumble.</description><description lang="pt_br">Asssista videos sem censura com o rumble.</description><disclaimer lang="en">We are not associated with rumble.com or the Kodi Team</disclaimer><disclaimer lang="pt_br">Não somos associados à rumble.com nem com o Kodi Team</disclaimer><website>https://github.com/azzy9/plugin.video.rumble</website><platform>all</platform><assets><icon>icon.png</icon><fanart>fanart.jpg</fanart></assets><news>See the changelog in the commits on Github</news></extension></addon>
<addon id="plugin.video.wedotv" name="WeDoTV" version="0.1.3" provider-name="azzy9"><requires><import addon="script.module.requests"/><import addon="script.module.six"/></requires><extension point="xbmc.python.pluginsource" library="addon.py"><provides>video</provides></extension><extension point="xbmc.addon.metadata"><summary lang="en_GB">WeDoTV</summary><description lang="en_GB">This addon allows you watch Movies and TV Series from WeDoTV</description><language>uk</language><website>https://github.com/azzy9/plugin.video.wedotv</website><platform>all</platform><license>GPL-3.0-only</license><news>See the changelog in the commits on Github</news><assets><icon>icon.png</icon><fanart>fanart.jpg</fanart></assets></extension></addon>
<addon id="repository.azzyaddons" name="AzzyAddons Repository" version="1.0.1" provider-name="azzy9"><extension point="xbmc.addon.repository" name="AzzyAddons add-on Repository"><dir><info compressed="false">https://raw.githubusercontent.com/azzyaddons/azzyaddons.github.io/master/addons.xml</info><checksum>https://raw.githubusercontent.com/azzyaddons/azzyaddons.github.io/master/addons.xml.md5</checksum><datadir zip="true">https://raw.githubusercontent.com/azzyaddons/azzyaddons.github.io/master/plugins/</datadir></dir></extension><extension point="xbmc.addon.metadata"><summary lang="en">Install AzzyAddons Add-ons</summary><description lang="en">Add-ons from AzzyAddons repository.</description><disclaimer lang="en">Repository has non-comercial nature. Created by enthusiasts, acting in good faith.</disclaimer><platform>all</platform></extension></addon>
</addons>